pyny_web/__init__.py
pyny_web/pyny.py
pyny_web-1.0.7.dist-info/LICENSE
pyny_web-1.0.7.dist-info/METADATA
pyny_web-1.0.7.dist-info/WHEEL
pyny_web-1.0.7.dist-info/top_level.txt
pyny_web-1.0.7.dist-info/RECORD
