Metadata-Version: 2.1
Name: pyny-web
Version: 1.0.7
Summary: Tiny Python3 based web server.
Home-page: https://github.com/zeppelsoftware/pyny
Author: Zeppel
Author-email: info@zeppel.eu
License: UNKNOWN
Platform: UNKNOWN
Classifier: Programming Language :: Python :: 3
Classifier: License :: OSI Approved :: MIT License
Classifier: Operating System :: OS Independent
Requires-Python: >=3.6
